llmsh/__init__.py
llmsh/__main__.py
llmsh/cli/__init__.py
llmsh/cli/app.py
llmsh/cli/error_handler.py
llmsh/cli/params.py
llmsh/cli/renderer.py
llmsh/cli/utils.py
llmsh/models/__init__.py
llmsh/models/message.py
llmsh/settings/__init__.py
llmsh/settings/settings.py
llmsh-0.2.dist-info/LICENSE
llmsh-0.2.dist-info/METADATA
llmsh-0.2.dist-info/WHEEL
llmsh-0.2.dist-info/entry_points.txt
llmsh-0.2.dist-info/RECORD
