Metadata-Version: 2.1
Name: llmsh
Version: 0.2
Summary: Command-line tool to use Large Language Models in your shell,including OpenAI, Anthropic, PalM, Mistral, Cohere, and more.
Home-page: https://github.com/vduseev/llmsh
License: Apache-2.0
Keywords: cli,llm,openai,ai,shell,console,command-line
Author: Vagiz Duseev
Author-email: vagiz@duseev.com
Maintainer: Vagiz Duseev
Maintainer-email: vagiz@duseev.com
Requires-Python: >=3.9,<4.0
Classifier: Development Status :: 3 - Alpha
Classifier: Environment :: Console
Classifier: License :: OSI Approved :: Apache Software License
Classifier: Operating System :: MacOS
Classifier: Operating System :: Microsoft :: Windows
Classifier: Operating System :: POSIX :: Linux
Classifier: Programming Language :: Python
Classifier: Programming Language :: Python :: 3
Classifier: Programming Language :: Python :: 3.9
Classifier: Programming Language :: Python :: 3.10
Classifier: Programming Language :: Python :: 3.11
Classifier: Programming Language :: Python :: 3.12
Classifier: Programming Language :: Python :: 3.13
Classifier: Topic :: Communications :: Chat
Requires-Dist: inquirer (>=3.2.4,<4.0.0)
Requires-Dist: litellm (>=1.34.18,<2.0.0)
Requires-Dist: prompt-toolkit (>=3.0.43,<4.0.0)
Requires-Dist: pydantic (>=2.6.4,<3.0.0)
Requires-Dist: pydantic-settings (>=2.2.1,<3.0.0)
Requires-Dist: rich (>=13.7.1,<14.0.0)
Requires-Dist: typer (>=0.12.1,<0.13.0)
Project-URL: Documentation, https://github.com/vduseev/llmsh
Project-URL: Repository, https://github.com/vduseev/llmsh
